[
  {
    "date": "2017-09-21",
    "venue": "KUD Channel Zero",
    "location": "Ljubljana, Slovenia",
    "info": "w/ Svemirko",
    "link": "https://www.ch0.org/cetrtek-21-9-ob-21-00-level-7-svemirko-m-o-r-v-e-r-n/"
  },
  {
    "date": "2018-12-27",
    "venue": "Gala Hala",
    "location": "Ljubljana, Slovenia",
    "info": "Domorodni četrtki",
    "link": "https://www.galahala.com/arhiv/domorodni-cetrtki-m-o-r-v-e-r-n/20516/"
  },
  {
    "date": "2019-02-12",
    "venue": "Klub Gromka",
    "location": "Ljubljana, Slovenia",
    "info": "w/ Žblj Mozaik + Rush to Relax",
    "link": "https://www.facebook.com/events/2536232916460746/"
  }
]